efb_msg_blocker_middleware/__init__.py
efb_msg_blocker_middleware/__version__.py
efb_msg_blocker_middleware/db.py
efb_msg_blocker_middleware-1.1.0.dist-info/METADATA
efb_msg_blocker_middleware-1.1.0.dist-info/WHEEL
efb_msg_blocker_middleware-1.1.0.dist-info/entry_points.txt
efb_msg_blocker_middleware-1.1.0.dist-info/top_level.txt
efb_msg_blocker_middleware-1.1.0.dist-info/RECORD
